pymysqls/__init__.py
pymysqls/DB/DB.py
pymysqls/DB/ST.py
pymysqls/DB/__init__.py
pymysqls/DOC/DOC.py
pymysqls/DOC/__init__.py
pymysqls/OTHER/MAIN.iu.py
pymysqls/OTHER/TESTW.iu.py
pymysqls/OTHER/__init__.py
pymysqls/TESTS/MAIN.py
pymysqls/TESTS/TESTW.py
pymysqls/TESTS/__init__.py
pymysqls-5.1.2.dist-info/METADATA
pymysqls-5.1.2.dist-info/WHEEL
pymysqls-5.1.2.dist-info/top_level.txt
pymysqls-5.1.2.dist-info/RECORD
